trapdoor
trapperkeeper
