Metadata-Version: 1.1
Name: trapperkeeper
Version: 0.6.1
Summary: SNMP Trap Daemon.
Home-page: https://github.com/dropbox/trapperkeeper
Author: Gary M. Josack
Author-email: gary@dropbox.com
License: Apache
Download-URL: https://github.com/dropbox/trapperkeeper/archive/master.tar.gz
Platform: UNKNOWN
Classifier: Programming Language :: Python
Classifier: Topic :: Software Development
Classifier: Topic :: Software Development :: Libraries
Classifier: Topic :: Software Development :: Libraries :: Python Modules
